{
    "metadata": {
        "workbook_filename": "CLW250025.xlsx",
        "worksheet_name": "Sheet1",
        "fob_compounding_input_mode": "standard",
        "fob_chunk_size": 2,
        "fob_intra_separator": "/",
        "fob_inter_separator": "\\n",
        "timestamp": "2025-07-25T14:08:28.050230"
    },
    "processed_tables_data": {
        "1": {
            "production_order_no": [
                "2412003-01",
                "2412003-01",
                "2503046-01",
                "2503046-01",
                "2503046-01",
                "2506001-01",
                "2506001-01",
                "2506038-01",
                "2506038-01",
                "2506038-01",
                "2506038-01",
                "2506038-01",
                "2506038-01",
                "2506038-01",
                "2506038-01",
                "2506038-01",
                "2506063-01",
                "2506063-01",
                "2506063-01",
                "2506063-01",
                "2506063-01",
                "2506063-01",
                "2506063-01",
                "2506063-01",
                "2506063-01",
                "2506063-01",
                "2507032-01"
            ],
            "po": [
                "PT20T10",
                "PT20T10",
                "PT23D52",
                "PT23D52",
                "PT23D52",
                "PT24S66",
                "PT24S66",
                "PT26032",
                "PT26041",
                "PT26041",
                "PT26042",
                "PT26042",
                "PT26042",
                "PT26042",
                "PT26044",
                "PT26047",
                "PT26802",
                "PT26802",
                "PT26802",
                "PT26802",
                "PT26802",
                "PT26802",
                "PT26802",
                "PT26802",
                "PT26802",
                "PT26802",
                "PT27B66"
            ],
            "reference_code": [
                "XPSY-FB-\u7070\u7eff39",
                "XPSY-FB-\u7070\u7eff39",
                "XPSY-FH-\u5976\u767d183",
                "XPSY-FH-\u5976\u767d183",
                "XPSY-FH-\u5976\u767d183",
                "XPSY-FH-\u5976\u767d183",
                "XPSY-FH-\u5976\u767d183",
                "XZSY-FB-\u84dd299",
                "XZSY-FB-\u84dd299",
                "XZSY-FB-\u84dd299",
                "XZSY-FB-\u84dd299",
                "XZSY-FB-\u84dd299",
                "XZSY-FB-\u84dd299",
                "XZSY-FB-\u84dd299",
                "XZSY-FB-\u84dd299",
                "XZSY-FB-\u84dd299",
                "XPSY-FB-\u6df1\u68d5751",
                "XPSY-FB-\u6df1\u68d5751",
                "XPSY-FB-\u6df1\u68d5751",
                "XPSY-FB-\u6df1\u68d5751",
                "XPSY-FB-\u6df1\u68d5751",
                "XPSY-FB-\u6df1\u68d5751",
                "XPSY-FB-\u6df1\u68d5751",
                "XPSY-FB-\u6df1\u68d5751",
                "XPSY-FB-\u6df1\u68d5751",
                "XPSY-FB-\u6df1\u68d5751",
                "XPSY-FB-\u6df1\u68d5751"
            ],
            "item": [
                140484,
                140484,
                140467,
                140467,
                140467,
                140467,
                140467,
                140491,
                140491,
                140491,
                140491,
                140491,
                140491,
                140491,
                140491,
                140491,
                140478,
                140478,
                140478,
                140478,
                140478,
                140478,
                140478,
                140478,
                140478,
                140478,
                140478
            ],
            "description": [
                "L BELZIANI BUFFALO STORM 54706",
                "L BELZIANI BUFFALO STORM 54706",
                "L GENOA  COCONUT 47704",
                "L GENOA  COCONUT 47704",
                "L GENOA  COCONUT 47704",
                "L GENOA  COCONUT 47704",
                "L GENOA  COCONUT 47704",
                "L LEESWORTH BUFFALO OCEAN U43809",
                "L LEESWORTH BUFFALO OCEAN U43809",
                "L LEESWORTH BUFFALO OCEAN U43809",
                "L LEESWORTH BUFFALO OCEAN U43809",
                "L LEESWORTH BUFFALO OCEAN U43809",
                "L LEESWORTH BUFFALO OCEAN U43809",
                "L LEESWORTH BUFFALO OCEAN U43809",
                "L LEESWORTH BUFFALO OCEAN U43809",
                "L LEESWORTH BUFFALO OCEAN U43809",
                "L LEESWORTH BUFFALO DARK BROWN",
                "L LEESWORTH BUFFALO DARK BROWN",
                "L LEESWORTH BUFFALO DARK BROWN",
                "L LEESWORTH BUFFALO DARK BROWN",
                "L LEESWORTH BUFFALO DARK BROWN",
                "L LEESWORTH BUFFALO DARK BROWN",
                "L LEESWORTH BUFFALO DARK BROWN",
                "L LEESWORTH BUFFALO DARK BROWN",
                "L LEESWORTH BUFFALO DARK BROWN",
                "L LEESWORTH BUFFALO DARK BROWN",
                "L LEESWORTH BUFFALO DARK BROWN"
            ],
            "pcs": [
                275,
                198,
                140,
                122,
                6,
                196,
                2,
                147,
                275,
                215,
                205,
                200,
                108,
                7,
                169,
                143,
                295,
                290,
                295,
                290,
                290,
                188,
                206,
                130,
                290,
                300,
                260
            ],
            "sqft": [
                10171,
                7358.9,
                7065.8,
                6635.1,
                293.7,
                11128.8,
                132.2,
                5551.4,
                10104.8,
                8102.5,
                7877.6,
                7535.2,
                4107.3,
                259.9,
                6381.9,
                5376.5,
                10932.6,
                10789.4,
                10920.5,
                10797,
                10839.6,
                6879.3,
                7512.1,
                4712.5,
                10713.4,
                10914,
                9331
            ],
            "pallet_count": [
                1,
                1,
                1,
                1,
                0,
                1,
                0,
                1,
                1,
                1,
                1,
                1,
                1,
                0,
                1,
                1,
                1,
                1,
                1,
                1,
                1,
                1,
                1,
                1,
                1,
                1,
                1
            ],
            "unit": [
                0.9,
                0.9,
                1.02,
                1.02,
                1.02,
                1.02,
                1.02,
                0.92,
                0.92,
                0.92,
                0.92,
                0.92,
                0.92,
                0.92,
                0.92,
                0.92,
                0.9,
                0.9,
                0.9,
                0.9,
                0.9,
                0.9,
                0.9,
                0.9,
                0.9,
                0.9,
                0.9
            ],
            "amount": [
                9153.9,
                6623.01,
                7207.116,
                6767.802,
                299.574,
                11351.376,
                134.844,
                5107.288,
                9296.416,
                7454.3,
                7247.392,
                6932.384,
                3778.716,
                239.108,
                5871.348,
                4946.38,
                9839.34,
                9710.46,
                9828.45,
                9717.3,
                9755.64,
                6191.37,
                6760.89,
                4241.25,
                9642.06,
                9822.6,
                8397.9
            ],
            "net": [
                "708.5",
                "495.5",
                "554",
                "509.4453",
                "25.0547",
                "868.6364",
                "8.8636",
                "411.5",
                "735.5",
                "589.5",
                "564",
                "546",
                "297.2348",
                "19.2652",
                "467",
                "387.5",
                "702.5",
                "699",
                "709",
                "692.5",
                "709",
                "447.5",
                "495.5",
                "285",
                "727",
                "738",
                "644.5"
            ],
            "gross": [
                "753.5",
                "540.5",
                "599",
                "552.3359",
                "27.1641",
                "913.1818",
                "9.3182",
                "456.5",
                "780.5",
                "634.5",
                "609",
                "591",
                "339.4957",
                "22.0043",
                "512",
                "432.5",
                "747.5",
                "744",
                "754",
                "737.5",
                "754",
                "492.5",
                "540.5",
                "330",
                "772",
                "783",
                "689.5"
            ],
            "cbm": [
                "2.2968",
                "1.9800",
                "2.0988",
                "2.2269",
                "0.1095",
                "2.7440",
                "0.0280",
                "1.7028",
                "2.2968",
                "2.1384",
                "1.9800",
                "2.1384",
                "1.4876",
                "0.0964",
                "1.8216",
                "1.7028",
                "2.3760",
                "2.3760",
                "2.2572",
                "2.4552",
                "2.3760",
                "1.9800",
                "1.7820",
                "2.3760",
                "2.6532",
                "2.2572",
                "2.2176"
            ],
            "remarks": [
                null,
                null,
                null,
                null,
                "Low selection if yes",
                null,
                "Low selection if yes",
                null,
                null,
                null,
                null,
                null,
                null,
                "Low selection if yes",
                null,
                null,
                null,
                null,
                null,
                null,
                null,
                null,
                null,
                null,
                null,
                null,
                null
            ]
        }
    },
    "standard_aggregation_results": {
        "('PT20T10', 140484, Decimal('0.9'), 'L BELZIANI BUFFALO STORM 54706')": {
            "sqft_sum": "17529.9",
            "amount_sum": "15776.91"
        },
        "('PT23D52', 140467, Decimal('1.02'), 'L GENOA  COCONUT 47704')": {
            "sqft_sum": "13994.6",
            "amount_sum": "14274.492"
        },
        "('PT24S66', 140467, Decimal('1.02'), 'L GENOA  COCONUT 47704')": {
            "sqft_sum": "11261.0",
            "amount_sum": "11486.220"
        },
        "('PT26032', 140491, Decimal('0.92'), 'L LEESWORTH BUFFALO OCEAN U43809')": {
            "sqft_sum": "5551.4",
            "amount_sum": "5107.288"
        },
        "('PT26041', 140491, Decimal('0.92'), 'L LEESWORTH BUFFALO OCEAN U43809')": {
            "sqft_sum": "18207.3",
            "amount_sum": "16750.716"
        },
        "('PT26042', 140491, Decimal('0.92'), 'L LEESWORTH BUFFALO OCEAN U43809')": {
            "sqft_sum": "19780.0",
            "amount_sum": "18197.600"
        },
        "('PT26044', 140491, Decimal('0.92'), 'L LEESWORTH BUFFALO OCEAN U43809')": {
            "sqft_sum": "6381.9",
            "amount_sum": "5871.348"
        },
        "('PT26047', 140491, Decimal('0.92'), 'L LEESWORTH BUFFALO OCEAN U43809')": {
            "sqft_sum": "5376.5",
            "amount_sum": "4946.38"
        },
        "('PT26802', 140478, Decimal('0.9'), 'L LEESWORTH BUFFALO DARK BROWN')": {
            "sqft_sum": "95010.4",
            "amount_sum": "85509.36"
        },
        "('PT27B66', 140478, Decimal('0.9'), 'L LEESWORTH BUFFALO DARK BROWN')": {
            "sqft_sum": "9331",
            "amount_sum": "8397.9"
        }
    },
    "custom_aggregation_results": {
        "('PT20T10', 140484, None, 'L BELZIANI BUFFALO STORM 54706')": {
            "sqft_sum": "17529.9",
            "amount_sum": "15776.91"
        },
        "('PT23D52', 140467, None, 'L GENOA  COCONUT 47704')": {
            "sqft_sum": "13994.6",
            "amount_sum": "14274.492"
        },
        "('PT24S66', 140467, None, 'L GENOA  COCONUT 47704')": {
            "sqft_sum": "11261.0",
            "amount_sum": "11486.220"
        },
        "('PT26032', 140491, None, 'L LEESWORTH BUFFALO OCEAN U43809')": {
            "sqft_sum": "5551.4",
            "amount_sum": "5107.288"
        },
        "('PT26041', 140491, None, 'L LEESWORTH BUFFALO OCEAN U43809')": {
            "sqft_sum": "18207.3",
            "amount_sum": "16750.716"
        },
        "('PT26042', 140491, None, 'L LEESWORTH BUFFALO OCEAN U43809')": {
            "sqft_sum": "19780.0",
            "amount_sum": "18197.600"
        },
        "('PT26044', 140491, None, 'L LEESWORTH BUFFALO OCEAN U43809')": {
            "sqft_sum": "6381.9",
            "amount_sum": "5871.348"
        },
        "('PT26047', 140491, None, 'L LEESWORTH BUFFALO OCEAN U43809')": {
            "sqft_sum": "5376.5",
            "amount_sum": "4946.38"
        },
        "('PT26802', 140478, None, 'L LEESWORTH BUFFALO DARK BROWN')": {
            "sqft_sum": "95010.4",
            "amount_sum": "85509.36"
        },
        "('PT27B66', 140478, None, 'L LEESWORTH BUFFALO DARK BROWN')": {
            "sqft_sum": "9331",
            "amount_sum": "8397.9"
        }
    },
    "final_fob_compounded_result": {
        "1": {
            "combined_po": "PT20T10/PT26032\nPT26041/PT26042\nPT26044/PT26047\nPT26802/PT27B66",
            "combined_item": "140478/140484\n140491",
            "combined_description": "L BELZIANI BUFFALO STORM 54706\nL LEESWORTH BUFFALO DARK BROWN\nL LEESWORTH BUFFALO OCEAN U43809",
            "total_sqft": "177168.4",
            "total_amount": "160557.502"
        },
        "2": {
            "combined_po": "PT23D52/PT24S66",
            "combined_item": "140467",
            "combined_description": "L GENOA  COCONUT 47704",
            "total_sqft": "25255.6",
            "total_amount": "25760.712"
        }
    }
}